sourmash_plugin_pangenomics.py
sourmash_plugin_pangenomics-0.3.2.dist-info/licenses/LICENSE
sourmash_plugin_pangenomics-0.3.2.dist-info/METADATA
sourmash_plugin_pangenomics-0.3.2.dist-info/WHEEL
sourmash_plugin_pangenomics-0.3.2.dist-info/entry_points.txt
sourmash_plugin_pangenomics-0.3.2.dist-info/top_level.txt
sourmash_plugin_pangenomics-0.3.2.dist-info/RECORD
