Metadata-Version: 2.4
Name: sourmash_plugin_pangenomics
Version: 0.3.2
Summary: sourmash plugin to do pangenomics.
Author-email: Colton Baumler <ccbaumler@ucdavis.edu>, Titus Brown <titus@idyll.org>
Requires-Python: >=3.11
License-File: LICENSE
Requires-Dist: sourmash<5,>=4.9.0
Requires-Dist: sourmash_utils>=0.3
Dynamic: license-file
